ts_demuxer/__init__.py
ts_demuxer/packet.py
ts_demuxer/pat_section.py
ts_demuxer/pes.py
ts_demuxer/pes_stream.py
ts_demuxer/pmt_section.py
ts_demuxer/psi.py
ts_demuxer/ts_demux.py
ts_demuxer-1.0.0.dist-info/LICENSE
ts_demuxer-1.0.0.dist-info/METADATA
ts_demuxer-1.0.0.dist-info/WHEEL
ts_demuxer-1.0.0.dist-info/top_level.txt
ts_demuxer-1.0.0.dist-info/RECORD
