Metadata-Version: 2.1
Name: ts-demuxer
Version: 1.0.0
Summary: ts demux
Home-page: https://gitee.com/xiao200/py_ts_demux.git
Author: xuhx20
Author-email: xuhx20@qq.com
License: BSD License
Platform: all
Classifier: Intended Audience :: Developers
Classifier: Operating System :: OS Independent
Classifier: Natural Language :: Chinese (Simplified)
Classifier: Programming Language :: Python
Classifier: Programming Language :: Python :: 3.8
Classifier: Topic :: Software Development :: Libraries
License-File: LICENSE
